beradio/__init__.py
beradio/commands.py
beradio/config.py
beradio/decoder.py
beradio/forward.py
beradio/gibberish.py
beradio/message.py
beradio/mqtt.py
beradio/network.py
beradio/protocol.py
beradio/publish.py
beradio/snowflake.py
beradio/subscribe.py
beradio/util.py
testing/__init__.py
testing/doctests_plus.py
beradio-0.14.0.dist-info/LICENSE
beradio-0.14.0.dist-info/METADATA
beradio-0.14.0.dist-info/WHEEL
beradio-0.14.0.dist-info/entry_points.txt
beradio-0.14.0.dist-info/top_level.txt
beradio-0.14.0.dist-info/RECORD
