Metadata-Version: 2.1
Name: beradio
Version: 0.14.0
Summary: BERadio is an encoding specification and implementation for efficient communication in constrained radio link environments. It is conceived and used for over-the-air communication within the Hiveeyes project.
Home-page: https://hiveeyes.org/docs/beradio/
Author: The Hiveeyes Developers
Author-email: hello@hiveeyes.org
License: AGPL 3, EUPL 1.2
Keywords: protocol rfm serial mqtt Bencode BERadio
Classifier: Development Status :: 4 - Beta
Classifier: Environment :: Console
Classifier: Intended Audience :: Developers
Classifier: Intended Audience :: Information Technology
Classifier: Intended Audience :: Science/Research
Classifier: License :: OSI Approved :: GNU Affero General Public License v3 or later (AGPLv3+)
Classifier: License :: OSI Approved :: European Union Public Licence 1.2 (EUPL 1.2)
Classifier: Natural Language :: English
Classifier: Operating System :: MacOS :: MacOS X
Classifier: Operating System :: POSIX :: Linux
Classifier: Programming Language :: Python
Classifier: Programming Language :: Python :: 3
Classifier: Programming Language :: Python :: 3.7
Classifier: Programming Language :: Python :: 3.8
Classifier: Programming Language :: Python :: 3.9
Classifier: Programming Language :: Python :: 3.10
Classifier: Programming Language :: Python :: 3.11
Classifier: Programming Language :: Python :: 3.12
Classifier: Topic :: Communications
Classifier: Topic :: Internet
Classifier: Topic :: Scientific/Engineering
Classifier: Topic :: Software Development :: Libraries
Classifier: Topic :: System :: Archiving
Classifier: Topic :: Terminals :: Serial
Classifier: Topic :: Text Processing
Classifier: Topic :: Utilities
License-File: LICENSE
Requires-Dist: pyserial <4
Requires-Dist: paho-mqtt <2
Requires-Dist: bencode.py <5
Requires-Dist: docopt <1
Requires-Dist: platformdirs <5
Requires-Dist: json-store <4,>=3.1
Provides-Extra: test
Requires-Dist: nose2 <1 ; extra == 'test'
Requires-Dist: nose2-cov ==1.0a4 ; extra == 'test'
Requires-Dist: jsonpointer <3 ; extra == 'test'
Requires-Dist: PyYAML <7 ; extra == 'test'
Requires-Dist: u-msgpack-python <3 ; extra == 'test'
